LICENSE
MANIFEST.in
README.rst
setup.cfg
setup.py
syncano_cli/__init__.py
syncano_cli/commands.py
syncano_cli/config.py
syncano_cli/main.py
syncano_cli.egg-info/PKG-INFO
syncano_cli.egg-info/SOURCES.txt
syncano_cli.egg-info/dependency_links.txt
syncano_cli.egg-info/entry_points.txt
syncano_cli.egg-info/requires.txt
syncano_cli.egg-info/top_level.txt
syncano_cli/account/__init__.py
syncano_cli/account/command.py
syncano_cli/account/commands.py
syncano_cli/base/__init__.py
syncano_cli/base/command.py
syncano_cli/base/connection.py
syncano_cli/base/data_parser.py
syncano_cli/base/exceptions.py
syncano_cli/config_commands/__init__.py
syncano_cli/config_commands/command.py
syncano_cli/config_commands/commands.py
syncano_cli/config_commands/exceptions.py
syncano_cli/custom_sockets/__init__.py
syncano_cli/custom_sockets/command.py
syncano_cli/custom_sockets/commands.py
syncano_cli/custom_sockets/exceptions.py
syncano_cli/custom_sockets/formatters.py
syncano_cli/custom_sockets/parsers.py
syncano_cli/custom_sockets/templates/__init__.py
syncano_cli/custom_sockets/templates/socket_template.py
syncano_cli/execute/__init__.py
syncano_cli/execute/commands.py
syncano_cli/execute/utils.py
syncano_cli/hosting/__init__.py
syncano_cli/hosting/command.py
syncano_cli/hosting/commands.py
syncano_cli/hosting/exceptions.py
syncano_cli/hosting/validators.py
syncano_cli/init/__init__.py
syncano_cli/init/commands.py
syncano_cli/init/helpers.py
syncano_cli/instance/__init__.py
syncano_cli/instance/command.py
syncano_cli/instance/commands.py
syncano_cli/instance/exceptions.py
syncano_cli/parse_to_syncano/__init__.py
syncano_cli/parse_to_syncano/commands.py
syncano_cli/parse_to_syncano/config.py
syncano_cli/parse_to_syncano/moses.py
syncano_cli/parse_to_syncano/migrations/__init__.py
syncano_cli/parse_to_syncano/migrations/aggregation.py
syncano_cli/parse_to_syncano/migrations/mixins.py
syncano_cli/parse_to_syncano/migrations/relation.py
syncano_cli/parse_to_syncano/migrations/transfer.py
syncano_cli/parse_to_syncano/parse/__init__.py
syncano_cli/parse_to_syncano/parse/connection.py
syncano_cli/parse_to_syncano/parse/constants.py
syncano_cli/parse_to_syncano/parse/rest_map.py
