Metadata-Version: 1.0
Name: syncano-cli
Version: 0.8
Summary: Syncano command line utilities
Home-page: https://github.com/Syncano/syncano-cli
Author: Marcin Swiderski, Sebastian Opalczynski
Author-email: marcin.swiderski@syncano.com, sebastian.opalczynski@syncano.com
License: MIT
Platform: UNKNOWN
